ZhongwenVocaloidChuangzuoRumenjiaochengV110Dg/README.md
ZhongwenVocaloidChuangzuoRumenjiaochengV110Dg/__init__.py
ZhongwenVocaloidChuangzuoRumenjiaochengV110Dg/__main__.py
ZhongwenVocaloidChuangzuoRumenjiaochengV110Dg/file.pdf
ZhongwenVocaloidChuangzuoRumenjiaochengV110Dg/index.html
zhongwen_vocaloid_chuangzuo_rumenjiaocheng_v1_1_0_dg-2024.3.5.0.dist-info/METADATA
zhongwen_vocaloid_chuangzuo_rumenjiaocheng_v1_1_0_dg-2024.3.5.0.dist-info/WHEEL
zhongwen_vocaloid_chuangzuo_rumenjiaocheng_v1_1_0_dg-2024.3.5.0.dist-info/entry_points.txt
zhongwen_vocaloid_chuangzuo_rumenjiaocheng_v1_1_0_dg-2024.3.5.0.dist-info/top_level.txt
zhongwen_vocaloid_chuangzuo_rumenjiaocheng_v1_1_0_dg-2024.3.5.0.dist-info/RECORD
